pyvino/__init__.py
pyvino/model/__init__.py
pyvino/model/face_recognition/__init__.py
pyvino/model/instance_segmentation/__init__.py
pyvino/model/object_detection/__init__.py
pyvino/model/pose_estimation/__init__.py
pyvino/model/reidentification/__init__.py
pyvino/model/super_resolution/__init__.py
pyvino/tests/__init__.py
pyvino/tests/detector/__init__.py
pyvino/tests/detector/test_detector.py
pyvino/tests/model/__init__.py
pyvino/tests/model/test_model.py
pyvino/util/__init__.py
pyvino/util/config.py
pyvino/util/image.py
pyvino/util/logger.py
pyvino/util/tester.py
pyvino-0.0.3.dist-info/METADATA
pyvino-0.0.3.dist-info/RECORD
pyvino-0.0.3.dist-info/WHEEL
pyvino-0.0.3.dist-info/top_level.txt
