Metadata-Version: 2.1
Name: pyvino
Version: 0.0.3
Summary: UNKNOWN
Home-page: https://github.com/hampen2929/pyvino
Author: hampen2929
Author-email: yuya.mochimaru.ym@gmail.com
License: Apache
Platform: UNKNOWN
Requires-Dist: numpy
Requires-Dist: pandas
Requires-Dist: pytest (==5.0.1)
Requires-Dist: matplotlib
Requires-Dist: pillow
Requires-Dist: googledrivedownloader
Requires-Dist: requests
Requires-Dist: jupytext
